NginxKaifaCongRumenDaoJingtong/README.md
NginxKaifaCongRumenDaoJingtong/__init__.py
NginxKaifaCongRumenDaoJingtong/__main__.py
NginxKaifaCongRumenDaoJingtong/file.epub
NginxKaifaCongRumenDaoJingtong/index.html
NginxKaifaCongRumenDaoJingtong/css/__init__.py
NginxKaifaCongRumenDaoJingtong/css/annotations.css
NginxKaifaCongRumenDaoJingtong/css/main.css
NginxKaifaCongRumenDaoJingtong/css/normalize.css
NginxKaifaCongRumenDaoJingtong/css/popup.css
NginxKaifaCongRumenDaoJingtong/font/__init__.py
NginxKaifaCongRumenDaoJingtong/font/fontello.eot
NginxKaifaCongRumenDaoJingtong/font/fontello.svg
NginxKaifaCongRumenDaoJingtong/font/fontello.ttf
NginxKaifaCongRumenDaoJingtong/font/fontello.woff
NginxKaifaCongRumenDaoJingtong/img/__init__.py
NginxKaifaCongRumenDaoJingtong/img/annotator-glyph-sprite.png
NginxKaifaCongRumenDaoJingtong/img/annotator-icon-sprite.png
NginxKaifaCongRumenDaoJingtong/img/apple-touch-icon.png
NginxKaifaCongRumenDaoJingtong/img/cancelfullscreen.png
NginxKaifaCongRumenDaoJingtong/img/close.png
NginxKaifaCongRumenDaoJingtong/img/fullscreen.png
NginxKaifaCongRumenDaoJingtong/img/loader.gif
NginxKaifaCongRumenDaoJingtong/img/menu-icon.png
NginxKaifaCongRumenDaoJingtong/img/save.png
NginxKaifaCongRumenDaoJingtong/img/saved.png
NginxKaifaCongRumenDaoJingtong/img/settings-s.png
NginxKaifaCongRumenDaoJingtong/img/settings.png
NginxKaifaCongRumenDaoJingtong/img/star.png
NginxKaifaCongRumenDaoJingtong/js/__init__.py
NginxKaifaCongRumenDaoJingtong/js/epub.js
NginxKaifaCongRumenDaoJingtong/js/epub.min.js
NginxKaifaCongRumenDaoJingtong/js/epub.min.map
NginxKaifaCongRumenDaoJingtong/js/hooks.min.js
NginxKaifaCongRumenDaoJingtong/js/hooks.min.map
NginxKaifaCongRumenDaoJingtong/js/reader.js
NginxKaifaCongRumenDaoJingtong/js/reader.js.map
NginxKaifaCongRumenDaoJingtong/js/reader.min.js
NginxKaifaCongRumenDaoJingtong/js/reader.min.map
NginxKaifaCongRumenDaoJingtong/js/hooks/__init__.py
NginxKaifaCongRumenDaoJingtong/js/hooks/extensions/__init__.py
nginx_kaifa_cong_rumen_dao_jingtong-2024.3.1.0.dist-info/METADATA
nginx_kaifa_cong_rumen_dao_jingtong-2024.3.1.0.dist-info/WHEEL
nginx_kaifa_cong_rumen_dao_jingtong-2024.3.1.0.dist-info/entry_points.txt
nginx_kaifa_cong_rumen_dao_jingtong-2024.3.1.0.dist-info/top_level.txt
nginx_kaifa_cong_rumen_dao_jingtong-2024.3.1.0.dist-info/RECORD
